fsdp_optimizers/__init__.py
fsdp_optimizers/kron.py
fsdp_optimizers/kron_mars.py
fsdp_optimizers/muon.py
fsdp_optimizers/soap.py
fsdp_optimizers/utils.py
fsdp_optimizers-0.0.1.dist-info/LICENSE
fsdp_optimizers-0.0.1.dist-info/METADATA
fsdp_optimizers-0.0.1.dist-info/WHEEL
fsdp_optimizers-0.0.1.dist-info/top_level.txt
fsdp_optimizers-0.0.1.dist-info/RECORD
